handle_credits/__init__.py
handle_credits/api.py
handle_credits/application.py
handle_credits/get_event.py
handle_credits/handler.py
handle_credits/sample_events.py
handle_credits/controllers/base_controller.py
handle_credits/controllers/handle_credits_controller.py
handle_credits/factories/base_factory.py
handle_credits/factories/factory.py
handle_credits/infra/aws_request.py
handle_credits/infra/rest.py
handle_credits/infra/script.py
handle_credits/infra/handle_credits/handle_credits.py
handle_credits/models/ad.py
handle_credits/models/credits.py
handle_credits/models/page.py
handle_credits/models/request.py
handle_credits/models/response.py
handle_credits/models/saved_file.py
handle_credits/models/video.py
handle_credits/services/base_service.py
handle_credits/services/handle_credits_service.py
handle_credits/services/speech_service.py
handle_credits/services/text_utils_service.py
handle_credits/services/time_service.py
handle_credits/utils/file.py
handle_credits/utils/helpers.py
handle_credits/utils/html.py
handle_credits/utils/json.py
handle_credits/utils/lambda_helpers.py
handle_credits/utils/markdown.py
handle_credits/utils/service_helper.py
handle_credits/utils/string_utils.py
handle_credits/utils/text.py
handle_credits/utils/time.py
handle_credits/utils/url.py
handle_credits/utils/video.py
video_bot_handle_credits-0.0.3.dist-info/LICENSE
video_bot_handle_credits-0.0.3.dist-info/METADATA
video_bot_handle_credits-0.0.3.dist-info/WHEEL
video_bot_handle_credits-0.0.3.dist-info/top_level.txt
video_bot_handle_credits-0.0.3.dist-info/RECORD
